Multiplier_2Bit/Multiplier_2Bit.v
module Multiplier_2Bit(
  input wire a0, a1,  // Number A (2-bits)
  input wire b0, b1,  // Number B (2-bits)

  output wire p0, p1, p2, p3  // Product Result (4-bits)
);

  assign {p3, p2, p1, p0} = {a1, a0} * {b1, b0};

endmodule

Multiplier_2Bit/Multiplier_2Bit_tb.v
`timescale 1ns / 1ps

module Multiplier_2Bit_tb;
  reg a0, a1;
  reg b0, b1;

  wire p0, p1, p2, p3;

  integer i, j;

  Multiplier_2Bit uut (
    .a0(a0), .a1(a1),
    .b0(b0), .b1(b1),
    .p0(p0), .p1(p1), .p2(p2), .p3(p3)
  );

  initial begin
    $dumpfile("Multiplier_2Bit_dump.vcd");
    $dumpvars(0, Multiplier_2Bit_tb);


    $display("Time\t A (a1a0) \t B (b1b0) \t Product (p3p2p1p0)");
    $display("----------------------------------------------------");

    for (i = 0; i < 4; i = i + 1) begin
      for (j = 0; j < 4; j = j + 1) begin
        {a1, a0} = i;
        {b1, b0} = j;
        #10;
        $display("%0dns\t %b%b (%d)  \t %b%b (%d)  \t %b%b%b%b (%d)",
          $time, a1, a0, i, b1, b0, j, p3, p2, p1, p0, {p3, p2, p1, p0});
      end
    end

    $finish;
  end
endmodule

Multiplier_2Bit/Multiplier_2Bit_dump.vcd
$date
	Sat Sep 26 14:36:13 2026
$end
$version
	Icarus Verilog
$end
$timescale
	1ps
$end
$scope module Multiplier_2Bit_tb $end
$var wire 1 ! p3 $end
$var wire 1 " p2 $end
$var wire 1 # p1 $end
$var wire 1 $ p0 $end
$var reg 1 % a0 $end
$var reg 1 & a1 $end
$var reg 1 ' b0 $end
$var reg 1 ( b1 $end
$var integer 32 ) i [31:0] $end
$var integer 32 * j [31:0] $end
$scope module uut $end
$var wire 1 % a0 $end
$var wire 1 & a1 $end
$var wire 1 ' b0 $end
$var wire 1 ( b1 $end
$var wire 1 ! p3 $end
$var wire 1 " p2 $end
$var wire 1 # p1 $end
$var wire 1 $ p0 $end
$upscope $end
$upscope $end
$enddefinitions $end
$comment Show the parameter values. $end
$dumpall
$end
#0
$dumpvars
b0 *
b0 )
0(
0'
0&
0%
0$
0#
0"
0!
$end
#10000
1'
b1 *
#20000
1(
0'
b10 *
#30000
1'
b11 *
#40000
0(
0'
1%
b1 )
b0 *
#50000
1$
1'
b1 *
#60000
1#
0$
1(
0'
b10 *
#70000
1$
1'
b11 *
#80000
0$
0#
0(
0'
1&
0%
b10 )
b0 *
#90000
1#
1'
b1 *
#100000
1"
0#
1(
0'
b10 *
#110000
1#
1'
b11 *
#120000
0#
0"
0(
0'
1%
b11 )
b0 *
#130000
1$
1#
1'
b1 *
#140000
1"
0$
1(
0'
b10 *
#150000
1$
0#
0"
1!
1'
b11 *
#160000
b100 )
b100 *
